{
    "id": "inter-op-500-7x7-05-491",
    "opt_time": 13041.0,
    "intra_instance_operation_entropy": 0.9363560438654527,
    "num_ops_per_job": 7,
    "max_op_time": 2083,
    "machine_types": [
        [
            3,
            5,
            1,
            2,
            4,
            1,
            3
        ],
        [
            0,
            0,
            0,
            2,
            2,
            0,
            5
        ],
        [
            6,
            0,
            4,
            3,
            3,
            2,
            1
        ],
        [
            4,
            1,
            1,
            6,
            3,
            3,
            6
        ],
        [
            5,
            2,
            6,
            4,
            1,
            1,
            0
        ],
        [
            3,
            1,
            0,
            4,
            6,
            2,
            1
        ],
        [
            1,
            0,
            3,
            4,
            2,
            2,
            6
        ]
    ],
    "durations": [
        [
            1363,
            1112,
            894,
            261,
            1544,
            1731,
            780
        ],
        [
            1531,
            519,
            1211,
            81,
            557,
            1983,
            727
        ],
        [
            84,
            206,
            1646,
            1268,
            1825,
            1987,
            1739
        ],
        [
            1646,
            140,
            981,
            832,
            9,
            9,
            1060
        ],
        [
            171,
            1595,
            465,
            1646,
            2007,
            685,
            1383
        ],
        [
            9,
            1126,
            272,
            185,
            465,
            2065,
            1801
        ],
        [
            1937,
            519,
            780,
            1160,
            557,
            1058,
            371
        ]
    ]
}