{
    "id": "inter-op-500-14x14-06-351",
    "opt_time": 26480.0,
    "intra_instance_operation_entropy": 0.9757017940163002,
    "num_ops_per_job": 14,
    "max_op_time": 2083,
    "machine_types": [
        [
            1,
            4,
            7,
            11,
            8,
            7,
            10,
            1,
            1,
            3,
            2,
            2,
            8,
            13
        ],
        [
            9,
            10,
            13,
            12,
            13,
            3,
            10,
            10,
            6,
            13,
            0,
            2,
            3,
            1
        ],
        [
            12,
            2,
            8,
            7,
            7,
            1,
            1,
            8,
            9,
            5,
            0,
            12,
            5,
            10
        ],
        [
            13,
            7,
            5,
            5,
            12,
            11,
            13,
            3,
            8,
            2,
            8,
            2,
            13,
            0
        ],
        [
            10,
            1,
            11,
            9,
            3,
            7,
            5,
            2,
            8,
            2,
            6,
            12,
            7,
            9
        ],
        [
            6,
            1,
            3,
            7,
            4,
            12,
            11,
            8,
            10,
            3,
            4,
            2,
            10,
            9
        ],
        [
            11,
            10,
            11,
            5,
            7,
            5,
            6,
            8,
            13,
            4,
            3,
            5,
            0,
            6
        ],
        [
            8,
            1,
            7,
            12,
            5,
            6,
            13,
            0,
            11,
            8,
            7,
            8,
            0,
            7
        ],
        [
            4,
            9,
            11,
            13,
            9,
            0,
            2,
            0,
            2,
            8,
            12,
            1,
            9,
            0
        ],
        [
            5,
            6,
            9,
            5,
            9,
            1,
            4,
            5,
            10,
            5,
            1,
            13,
            8,
            2
        ],
        [
            9,
            9,
            2,
            0,
            13,
            10,
            0,
            9,
            5,
            12,
            0,
            2,
            5,
            7
        ],
        [
            13,
            4,
            1,
            3,
            12,
            11,
            1,
            0,
            12,
            9,
            3,
            0,
            4,
            2
        ],
        [
            6,
            6,
            13,
            11,
            1,
            13,
            0,
            5,
            2,
            6,
            0,
            10,
            4,
            9
        ],
        [
            3,
            10,
            0,
            11,
            8,
            13,
            4,
            0,
            8,
            0,
            10,
            0,
            9,
            5
        ]
    ],
    "durations": [
        [
            778,
            1346,
            1388,
            96,
            1628,
            1941,
            95,
            1752,
            15,
            187,
            694,
            787,
            2046,
            1280
        ],
        [
            1444,
            1910,
            490,
            707,
            490,
            1118,
            701,
            890,
            870,
            975,
            1833,
            1600,
            322,
            997
        ],
        [
            1301,
            479,
            1618,
            352,
            1263,
            24,
            1800,
            939,
            901,
            1254,
            1869,
            594,
            474,
            1216
        ],
        [
            689,
            49,
            1705,
            1404,
            1108,
            338,
            397,
            164,
            947,
            916,
            1404,
            238,
            512,
            793
        ],
        [
            789,
            334,
            1771,
            1679,
            344,
            1005,
            1254,
            1166,
            1686,
            916,
            1501,
            1867,
            1251,
            935
        ],
        [
            1256,
            1801,
            1614,
            1719,
            473,
            1968,
            959,
            2009,
            1805,
            1118,
            306,
            1505,
            1552,
            2064
        ],
        [
            645,
            890,
            1154,
            225,
            1702,
            1962,
            256,
            2009,
            1277,
            369,
            1377,
            275,
            1584,
            53
        ],
        [
            1827,
            225,
            1784,
            2023,
            1466,
            1201,
            1908,
            550,
            1613,
            2009,
            661,
            914,
            1959,
            23
        ],
        [
            429,
            901,
            506,
            1174,
            370,
            54,
            939,
            1431,
            321,
            384,
            136,
            2022,
            1953,
            74
        ],
        [
            1735,
            907,
            608,
            1985,
            420,
            559,
            1346,
            275,
            978,
            1254,
            1449,
            1661,
            1231,
            238
        ],
        [
            807,
            901,
            1098,
            912,
            244,
            456,
            1117,
            193,
            31,
            1822,
            1956,
            1166,
            405,
            826
        ],
        [
            1284,
            2045,
            1271,
            1961,
            294,
            503,
            1115,
            1162,
            811,
            411,
            1288,
            1746,
            2045,
            1610
        ],
        [
            229,
            1038,
            1200,
            1341,
            1521,
            1855,
            1862,
            2015,
            939,
            1226,
            265,
            1842,
            1564,
            72
        ],
        [
            380,
            1377,
            1869,
            2010,
            1869,
            179,
            1436,
            1439,
            784,
            1017,
            1820,
            819,
            911,
            1817
        ]
    ]
}