{
    "id": "inter-op-500-9x9-04-164",
    "opt_time": 29215.0,
    "intra_instance_operation_entropy": 0.8468842722993217,
    "num_ops_per_job": 9,
    "max_op_time": 2083,
    "machine_types": [
        [
            7,
            0,
            0,
            6,
            1,
            2,
            6,
            7,
            5
        ],
        [
            5,
            7,
            8,
            1,
            5,
            7,
            0,
            7,
            8
        ],
        [
            0,
            0,
            7,
            0,
            3,
            0,
            3,
            3,
            8
        ],
        [
            0,
            3,
            0,
            0,
            6,
            0,
            1,
            4,
            5
        ],
        [
            2,
            1,
            7,
            8,
            1,
            0,
            5,
            1,
            1
        ],
        [
            0,
            6,
            2,
            0,
            7,
            4,
            2,
            4,
            7
        ],
        [
            8,
            0,
            1,
            6,
            1,
            0,
            5,
            7,
            2
        ],
        [
            0,
            8,
            0,
            4,
            6,
            3,
            8,
            8,
            2
        ],
        [
            4,
            8,
            0,
            7,
            1,
            5,
            1,
            0,
            1
        ]
    ],
    "durations": [
        [
            375,
            931,
            931,
            206,
            1462,
            149,
            1123,
            1609,
            423
        ],
        [
            328,
            2069,
            1748,
            1706,
            280,
            772,
            1879,
            1609,
            1748
        ],
        [
            931,
            1586,
            1699,
            1586,
            154,
            948,
            1804,
            1459,
            444
        ],
        [
            1879,
            1958,
            1586,
            2037,
            2003,
            931,
            1484,
            257,
            179
        ],
        [
            473,
            1462,
            1699,
            444,
            1081,
            1576,
            1541,
            1068,
            1484
        ],
        [
            931,
            206,
            1197,
            753,
            185,
            257,
            1379,
            257,
            174
        ],
        [
            444,
            2037,
            1484,
            642,
            470,
            1879,
            423,
            772,
            1197
        ],
        [
            753,
            955,
            1879,
            257,
            112,
            154,
            1213,
            1782,
            1379
        ],
        [
            192,
            955,
            2037,
            2069,
            1344,
            328,
            1081,
            1675,
            470
        ]
    ]
}