{
    "id": "inter-op-500-7x7-07-79",
    "opt_time": 16403.0,
    "intra_instance_operation_entropy": 0.9854609311384482,
    "num_ops_per_job": 7,
    "max_op_time": 2083,
    "machine_types": [
        [
            4,
            2,
            6,
            2,
            6,
            5,
            2
        ],
        [
            3,
            6,
            2,
            2,
            2,
            0,
            2
        ],
        [
            2,
            2,
            2,
            0,
            2,
            6,
            4
        ],
        [
            5,
            3,
            5,
            6,
            2,
            6,
            6
        ],
        [
            0,
            0,
            3,
            5,
            2,
            0,
            1
        ],
        [
            2,
            2,
            1,
            5,
            0,
            6,
            0
        ],
        [
            5,
            2,
            4,
            3,
            5,
            2,
            5
        ]
    ],
    "durations": [
        [
            1748,
            549,
            2024,
            606,
            956,
            1559,
            827
        ],
        [
            952,
            962,
            944,
            46,
            1835,
            249,
            1709
        ],
        [
            1834,
            514,
            942,
            385,
            2056,
            2007,
            1801
        ],
        [
            869,
            718,
            1762,
            1295,
            514,
            213,
            1681
        ],
        [
            1020,
            1545,
            283,
            1940,
            1895,
            1180,
            1623
        ],
        [
            845,
            327,
            1623,
            880,
            512,
            476,
            1448
        ],
        [
            115,
            64,
            1039,
            1228,
            257,
            896,
            465
        ]
    ]
}