{
    "id": "inter-op-500-11x11-06-474",
    "opt_time": 21896.0,
    "intra_instance_operation_entropy": 0.9689434484121273,
    "num_ops_per_job": 11,
    "max_op_time": 2083,
    "machine_types": [
        [
            1,
            8,
            7,
            2,
            10,
            8,
            10,
            1,
            10,
            8,
            3
        ],
        [
            1,
            3,
            2,
            5,
            5,
            8,
            4,
            2,
            10,
            10,
            0
        ],
        [
            7,
            5,
            5,
            10,
            10,
            2,
            1,
            1,
            9,
            7,
            0
        ],
        [
            0,
            0,
            7,
            5,
            8,
            10,
            1,
            7,
            7,
            2,
            6
        ],
        [
            8,
            9,
            8,
            7,
            7,
            3,
            7,
            2,
            10,
            4,
            2
        ],
        [
            2,
            2,
            10,
            6,
            0,
            2,
            10,
            3,
            6,
            3,
            10
        ],
        [
            7,
            7,
            10,
            8,
            1,
            3,
            2,
            10,
            8,
            4,
            0
        ],
        [
            1,
            9,
            5,
            3,
            9,
            6,
            7,
            1,
            6,
            3,
            4
        ],
        [
            9,
            9,
            4,
            6,
            2,
            3,
            3,
            0,
            7,
            1,
            2
        ],
        [
            2,
            8,
            5,
            10,
            8,
            2,
            5,
            5,
            9,
            1,
            2
        ],
        [
            8,
            8,
            1,
            1,
            4,
            9,
            2,
            2,
            2,
            0,
            2
        ]
    ],
    "durations": [
        [
            646,
            1694,
            317,
            1891,
            112,
            64,
            1130,
            1849,
            583,
            751,
            1463
        ],
        [
            573,
            2073,
            1842,
            409,
            599,
            750,
            366,
            1978,
            1065,
            112,
            44
        ],
        [
            1489,
            1112,
            1725,
            449,
            506,
            1308,
            1218,
            869,
            1353,
            1958,
            1401
        ],
        [
            286,
            2040,
            209,
            783,
            1694,
            1659,
            1201,
            1676,
            256,
            2021,
            40
        ],
        [
            1411,
            1435,
            289,
            381,
            43,
            1349,
            1511,
            1373,
            1687,
            647,
            1600
        ],
        [
            1066,
            190,
            2010,
            462,
            787,
            263,
            230,
            2073,
            1654,
            806,
            225
        ],
        [
            317,
            1459,
            1381,
            304,
            525,
            176,
            1600,
            1581,
            1586,
            373,
            707
        ],
        [
            522,
            1135,
            1846,
            1556,
            1750,
            1355,
            1393,
            811,
            1637,
            1520,
            1075
        ],
        [
            1077,
            1946,
            1260,
            1710,
            996,
            176,
            1706,
            1130,
            1295,
            876,
            1107
        ],
        [
            572,
            743,
            159,
            449,
            1372,
            64,
            1997,
            159,
            1043,
            1758,
            190
        ],
        [
            751,
            574,
            518,
            573,
            1153,
            216,
            629,
            692,
            1107,
            44,
            589
        ]
    ]
}