{
    "id": "inter-op-500-8x8-04-394",
    "opt_time": 22357.0,
    "intra_instance_operation_entropy": 0.8671365885191307,
    "num_ops_per_job": 8,
    "max_op_time": 2083,
    "machine_types": [
        [
            3,
            7,
            3,
            6,
            2,
            7,
            6,
            2
        ],
        [
            6,
            2,
            7,
            5,
            0,
            2,
            0,
            2
        ],
        [
            3,
            6,
            2,
            0,
            0,
            0,
            0,
            4
        ],
        [
            4,
            2,
            3,
            2,
            7,
            2,
            4,
            7
        ],
        [
            3,
            3,
            2,
            5,
            3,
            1,
            0,
            3
        ],
        [
            3,
            3,
            0,
            2,
            1,
            5,
            0,
            0
        ],
        [
            2,
            7,
            2,
            6,
            3,
            3,
            2,
            2
        ],
        [
            7,
            6,
            2,
            4,
            4,
            2,
            7,
            7
        ]
    ],
    "durations": [
        [
            218,
            1039,
            1807,
            843,
            1739,
            1531,
            266,
            209
        ],
        [
            1137,
            1443,
            1039,
            2047,
            519,
            1409,
            1291,
            1922
        ],
        [
            1807,
            1734,
            1504,
            1054,
            967,
            1601,
            1812,
            1524
        ],
        [
            892,
            569,
            134,
            209,
            663,
            1443,
            892,
            1531
        ],
        [
            134,
            1262,
            1409,
            2047,
            1262,
            748,
            967,
            797
        ],
        [
            875,
            797,
            1601,
            1725,
            748,
            807,
            394,
            1291
        ],
        [
            1040,
            1081,
            1922,
            1734,
            875,
            218,
            1409,
            1040
        ],
        [
            1778,
            2044,
            1443,
            991,
            1854,
            1922,
            1039,
            1678
        ]
    ]
}