{
    "id": "inter-op-500-8x8-07-411",
    "opt_time": 13960.0,
    "intra_instance_operation_entropy": 0.9791666666666669,
    "num_ops_per_job": 8,
    "max_op_time": 2083,
    "machine_types": [
        [
            6,
            7,
            1,
            0,
            0,
            5,
            2,
            1
        ],
        [
            1,
            2,
            1,
            5,
            2,
            2,
            2,
            2
        ],
        [
            1,
            4,
            1,
            1,
            2,
            7,
            4,
            0
        ],
        [
            3,
            3,
            0,
            3,
            0,
            3,
            3,
            5
        ],
        [
            0,
            7,
            2,
            5,
            7,
            5,
            4,
            6
        ],
        [
            3,
            2,
            4,
            3,
            3,
            0,
            4,
            5
        ],
        [
            0,
            0,
            0,
            5,
            0,
            5,
            7,
            1
        ],
        [
            5,
            5,
            5,
            3,
            0,
            2,
            7,
            4
        ]
    ],
    "durations": [
        [
            1826,
            103,
            515,
            1412,
            313,
            515,
            1015,
            411
        ],
        [
            1938,
            1509,
            1262,
            1860,
            1471,
            35,
            1660,
            1783
        ],
        [
            741,
            234,
            1592,
            246,
            821,
            652,
            572,
            157
        ],
        [
            912,
            1923,
            571,
            111,
            313,
            983,
            2067,
            707
        ],
        [
            47,
            1464,
            1380,
            707,
            28,
            601,
            1422,
            19
        ],
        [
            1246,
            1531,
            1646,
            1343,
            1980,
            1373,
            661,
            933
        ],
        [
            1206,
            456,
            1730,
            1788,
            1705,
            226,
            64,
            1310
        ],
        [
            1860,
            1372,
            43,
            1489,
            430,
            1509,
            839,
            1137
        ]
    ]
}