{
    "id": "inter-op-500-11x11-04-218",
    "opt_time": 20952.0,
    "intra_instance_operation_entropy": 0.8230038563254378,
    "num_ops_per_job": 11,
    "max_op_time": 2083,
    "machine_types": [
        [
            6,
            10,
            5,
            9,
            7,
            0,
            3,
            3,
            4,
            0,
            6
        ],
        [
            0,
            10,
            8,
            10,
            0,
            3,
            6,
            0,
            8,
            1,
            4
        ],
        [
            8,
            8,
            4,
            4,
            6,
            4,
            4,
            8,
            9,
            8,
            6
        ],
        [
            0,
            1,
            5,
            9,
            1,
            9,
            6,
            4,
            3,
            0,
            7
        ],
        [
            2,
            4,
            9,
            6,
            0,
            9,
            7,
            3,
            0,
            5,
            0
        ],
        [
            10,
            4,
            5,
            0,
            10,
            3,
            6,
            8,
            10,
            4,
            0
        ],
        [
            10,
            0,
            6,
            4,
            5,
            0,
            6,
            3,
            2,
            9,
            4
        ],
        [
            9,
            9,
            6,
            8,
            7,
            6,
            9,
            6,
            4,
            9,
            10
        ],
        [
            0,
            10,
            0,
            8,
            3,
            2,
            10,
            1,
            1,
            9,
            1
        ],
        [
            0,
            6,
            6,
            7,
            0,
            6,
            8,
            3,
            0,
            7,
            7
        ],
        [
            0,
            8,
            9,
            9,
            7,
            7,
            3,
            9,
            2,
            0,
            3
        ]
    ],
    "durations": [
        [
            1679,
            1242,
            817,
            1261,
            1875,
            566,
            328,
            844,
            1377,
            190,
            2067
        ],
        [
            1676,
            1224,
            1916,
            1651,
            1047,
            2034,
            1971,
            1676,
            1396,
            1130,
            1377
        ],
        [
            1396,
            1916,
            1942,
            1377,
            19,
            354,
            1302,
            1749,
            304,
            1400,
            671
        ],
        [
            190,
            1130,
            649,
            1022,
            1245,
            311,
            785,
            1942,
            1294,
            1670,
            1298
        ],
        [
            85,
            1942,
            29,
            1485,
            443,
            29,
            241,
            156,
            566,
            817,
            1047
        ],
        [
            1242,
            354,
            817,
            1670,
            1224,
            1385,
            1971,
            700,
            1651,
            627,
            1676
        ],
        [
            1224,
            566,
            785,
            1942,
            1926,
            566,
            690,
            1385,
            1842,
            29,
            1302
        ],
        [
            1896,
            42,
            690,
            322,
            1298,
            1485,
            42,
            671,
            1377,
            304,
            1224
        ],
        [
            1047,
            1651,
            190,
            322,
            1385,
            4,
            1224,
            791,
            1130,
            304,
            1130
        ],
        [
            1225,
            1971,
            2046,
            143,
            443,
            671,
            1749,
            2034,
            1670,
            122,
            1902
        ],
        [
            443,
            1916,
            311,
            311,
            122,
            1337,
            328,
            42,
            85,
            1676,
            844
        ]
    ]
}