{
    "id": "inter-op-500-12x12-06-64",
    "opt_time": 25521.0,
    "intra_instance_operation_entropy": 0.9728805469505847,
    "num_ops_per_job": 12,
    "max_op_time": 2083,
    "machine_types": [
        [
            8,
            6,
            10,
            3,
            6,
            2,
            5,
            8,
            6,
            11,
            7,
            4
        ],
        [
            7,
            9,
            10,
            6,
            6,
            2,
            9,
            1,
            9,
            11,
            5,
            1
        ],
        [
            4,
            10,
            2,
            9,
            4,
            6,
            8,
            3,
            0,
            5,
            7,
            0
        ],
        [
            9,
            7,
            11,
            2,
            11,
            9,
            10,
            7,
            3,
            9,
            6,
            11
        ],
        [
            2,
            8,
            2,
            0,
            1,
            9,
            5,
            0,
            4,
            9,
            4,
            6
        ],
        [
            0,
            4,
            3,
            4,
            0,
            2,
            10,
            11,
            4,
            4,
            5,
            9
        ],
        [
            4,
            2,
            9,
            2,
            10,
            7,
            1,
            9,
            10,
            7,
            11,
            8
        ],
        [
            11,
            11,
            11,
            0,
            2,
            0,
            8,
            11,
            4,
            10,
            11,
            6
        ],
        [
            8,
            4,
            8,
            7,
            9,
            1,
            10,
            7,
            9,
            1,
            0,
            8
        ],
        [
            4,
            4,
            0,
            1,
            10,
            9,
            5,
            6,
            1,
            9,
            6,
            4
        ],
        [
            8,
            11,
            10,
            10,
            4,
            3,
            5,
            1,
            8,
            9,
            9,
            9
        ],
        [
            4,
            8,
            11,
            1,
            10,
            9,
            0,
            2,
            1,
            9,
            0,
            3
        ]
    ],
    "durations": [
        [
            970,
            1068,
            1641,
            1705,
            2012,
            424,
            503,
            1479,
            675,
            325,
            199,
            63
        ],
        [
            757,
            1238,
            1718,
            1,
            1878,
            357,
            1259,
            1705,
            1238,
            1806,
            1738,
            465
        ],
        [
            2052,
            1871,
            1828,
            1392,
            1756,
            2012,
            2011,
            1880,
            1118,
            206,
            413,
            1759
        ],
        [
            1203,
            1736,
            1703,
            463,
            1360,
            906,
            1259,
            681,
            184,
            303,
            137,
            932
        ],
        [
            252,
            212,
            1438,
            857,
            1683,
            1764,
            1581,
            1118,
            1506,
            781,
            331,
            122
        ],
        [
            843,
            999,
            384,
            230,
            1286,
            1144,
            1718,
            1609,
            1458,
            1858,
            1735,
            1584
        ],
        [
            420,
            1358,
            842,
            929,
            734,
            1237,
            990,
            1852,
            894,
            826,
            817,
            552
        ],
        [
            932,
            629,
            866,
            1799,
            930,
            1286,
            2011,
            725,
            321,
            1641,
            97,
            1390
        ],
        [
            900,
            1110,
            1022,
            1257,
            67,
            630,
            1891,
            219,
            1484,
            345,
            691,
            96
        ],
        [
            63,
            72,
            1759,
            655,
            1324,
            1630,
            739,
            1478,
            1109,
            1271,
            1424,
            618
        ],
        [
            1680,
            635,
            473,
            782,
            112,
            235,
            30,
            395,
            300,
            1203,
            2076,
            693
        ],
        [
            72,
            1811,
            5,
            272,
            1112,
            258,
            1458,
            1828,
            42,
            1824,
            967,
            384
        ]
    ]
}