{
    "id": "inter-op-500-12x12-04-46",
    "opt_time": 25506.0,
    "intra_instance_operation_entropy": 0.8294841449505344,
    "num_ops_per_job": 12,
    "max_op_time": 2083,
    "machine_types": [
        [
            6,
            5,
            10,
            6,
            7,
            6,
            1,
            2,
            5,
            1,
            6,
            1
        ],
        [
            1,
            5,
            8,
            9,
            1,
            9,
            7,
            0,
            2,
            6,
            7,
            2
        ],
        [
            10,
            11,
            7,
            10,
            11,
            1,
            11,
            1,
            10,
            8,
            6,
            3
        ],
        [
            9,
            3,
            2,
            0,
            7,
            5,
            9,
            0,
            0,
            1,
            11,
            0
        ],
        [
            2,
            4,
            5,
            8,
            2,
            9,
            7,
            7,
            8,
            8,
            5,
            11
        ],
        [
            11,
            1,
            6,
            8,
            7,
            0,
            5,
            2,
            2,
            6,
            7,
            7
        ],
        [
            4,
            10,
            1,
            8,
            9,
            6,
            1,
            8,
            3,
            8,
            0,
            6
        ],
        [
            1,
            10,
            9,
            3,
            1,
            5,
            5,
            2,
            10,
            8,
            9,
            8
        ],
        [
            1,
            4,
            5,
            4,
            1,
            6,
            1,
            9,
            8,
            11,
            11,
            8
        ],
        [
            3,
            7,
            8,
            10,
            4,
            5,
            10,
            4,
            7,
            3,
            11,
            0
        ],
        [
            5,
            3,
            9,
            0,
            6,
            7,
            8,
            4,
            4,
            10,
            1,
            11
        ],
        [
            8,
            6,
            5,
            7,
            0,
            2,
            10,
            2,
            8,
            6,
            3,
            10
        ]
    ],
    "durations": [
        [
            1194,
            941,
            2031,
            571,
            154,
            188,
            1636,
            1005,
            46,
            181,
            119,
            1580
        ],
        [
            181,
            310,
            747,
            882,
            1364,
            244,
            154,
            1080,
            1027,
            119,
            1412,
            681
        ],
        [
            168,
            1941,
            822,
            897,
            614,
            1636,
            1941,
            2026,
            908,
            67,
            571,
            1720
        ],
        [
            349,
            873,
            1027,
            1224,
            1412,
            1588,
            882,
            879,
            30,
            2026,
            460,
            1224
        ],
        [
            1194,
            725,
            1041,
            860,
            1194,
            1354,
            2080,
            714,
            689,
            860,
            275,
            460
        ],
        [
            1941,
            1636,
            7,
            291,
            1412,
            1080,
            310,
            1027,
            681,
            1194,
            154,
            1412
        ],
        [
            725,
            897,
            1364,
            67,
            1354,
            571,
            1580,
            1446,
            1013,
            1446,
            30,
            188
        ],
        [
            1580,
            1471,
            778,
            2050,
            1636,
            132,
            310,
            1584,
            2031,
            747,
            349,
            222
        ],
        [
            2026,
            763,
            1041,
            763,
            1838,
            7,
            1636,
            882,
            860,
            335,
            1993,
            291
        ],
        [
            1013,
            154,
            291,
            897,
            725,
            941,
            897,
            787,
            1734,
            523,
            968,
            30
        ],
        [
            132,
            1013,
            244,
            1496,
            1194,
            1734,
            747,
            763,
            725,
            897,
            1580,
            614
        ],
        [
            67,
            1204,
            359,
            1734,
            1224,
            1584,
            852,
            1584,
            1784,
            1204,
            1396,
            1471
        ]
    ]
}