{
    "id": "inter-op-500-12x12-04-285",
    "opt_time": 24208.0,
    "intra_instance_operation_entropy": 0.8050579626064989,
    "num_ops_per_job": 12,
    "max_op_time": 2083,
    "machine_types": [
        [
            6,
            10,
            4,
            6,
            8,
            1,
            6,
            8,
            7,
            2,
            8,
            3
        ],
        [
            4,
            9,
            7,
            0,
            11,
            8,
            7,
            8,
            7,
            3,
            0,
            10
        ],
        [
            2,
            0,
            2,
            3,
            2,
            1,
            0,
            11,
            0,
            9,
            5,
            9
        ],
        [
            8,
            10,
            0,
            3,
            3,
            8,
            5,
            9,
            7,
            0,
            1,
            9
        ],
        [
            3,
            8,
            7,
            7,
            8,
            5,
            1,
            5,
            3,
            10,
            6,
            5
        ],
        [
            0,
            5,
            5,
            8,
            10,
            8,
            8,
            8,
            1,
            0,
            8,
            9
        ],
        [
            8,
            11,
            2,
            3,
            0,
            3,
            5,
            9,
            4,
            5,
            1,
            4
        ],
        [
            8,
            11,
            6,
            7,
            6,
            6,
            7,
            4,
            0,
            8,
            4,
            9
        ],
        [
            5,
            2,
            8,
            7,
            8,
            0,
            6,
            1,
            7,
            0,
            6,
            8
        ],
        [
            8,
            2,
            0,
            4,
            4,
            3,
            3,
            0,
            4,
            2,
            10,
            5
        ],
        [
            8,
            0,
            3,
            6,
            1,
            10,
            0,
            6,
            8,
            11,
            8,
            11
        ],
        [
            9,
            8,
            6,
            0,
            10,
            1,
            8,
            5,
            0,
            8,
            3,
            8
        ]
    ],
    "durations": [
        [
            1194,
            1471,
            725,
            188,
            1784,
            1580,
            1619,
            1279,
            154,
            1027,
            67,
            523
        ],
        [
            763,
            882,
            714,
            449,
            392,
            291,
            154,
            860,
            2080,
            1396,
            1496,
            2031
        ],
        [
            681,
            879,
            1194,
            873,
            1194,
            181,
            1080,
            1689,
            879,
            220,
            46,
            220
        ],
        [
            291,
            897,
            1780,
            219,
            1720,
            747,
            1843,
            244,
            1412,
            362,
            1580,
            244
        ],
        [
            1396,
            1784,
            154,
            1734,
            747,
            46,
            1364,
            359,
            873,
            897,
            119,
            46
        ],
        [
            449,
            571,
            132,
            291,
            168,
            291,
            1446,
            1279,
            1364,
            1496,
            747,
            882
        ],
        [
            222,
            357,
            1027,
            873,
            1780,
            873,
            1588,
            1066,
            763,
            359,
            1580,
            137
        ],
        [
            860,
            357,
            188,
            154,
            188,
            188,
            1476,
            763,
            449,
            747,
            725,
            1066
        ],
        [
            1843,
            1584,
            242,
            154,
            1784,
            1496,
            1194,
            427,
            2080,
            1080,
            1194,
            222
        ],
        [
            1989,
            1027,
            1126,
            725,
            725,
            1720,
            873,
            1126,
            137,
            681,
            897,
            359
        ],
        [
            222,
            1080,
            1720,
            188,
            181,
            1471,
            1126,
            1619,
            860,
            460,
            860,
            1941
        ],
        [
            244,
            860,
            7,
            879,
            897,
            1364,
            747,
            1843,
            1496,
            1784,
            1668,
            747
        ]
    ]
}